<?xml version="1.0" encoding="UTF-8"?>
<objects serializationModel="Studio.02.01.00">
	<object class="AudioFile" id="{17975968-a189-4cae-b2a2-2e1dd1891acc}">
		<property name="assetPath">
			<value>Compress_Extra/taunt_21.wav</value>
		</property>
		<property name="frequencyInKHz">
			<value>11.0249996</value>
		</property>
		<property name="channelCount">
			<value>1</value>
		</property>
		<property name="length">
			<value>3.1628117913832199</value>
		</property>
		<relationship name="masterAssetFolder">
			<destination>{eb2a4d4a-1287-481b-8086-c8771a725107}</destination>
		</relationship>
	</object>
</objects>
